Metadata-Version: 2.1
Name: crow-serial
Version: 0.4.0
Summary: Host implementation of the Crow serial protocol.
Home-page: http://siedell.com/projects/Crow
Author: Chris Siedell
Author-email: chris@siedell.com
License: MIT
Project-URL: Source, https://github.com/chris-siedell/PyCrow
Project-URL: Homepage, http://siedell.com/projects/Crow
Keywords: serial protocol
Platform: UNKNOWN
Classifier: Development Status :: 3 - Alpha
Classifier: License :: OSI Approved :: MIT License
Classifier: Programming Language :: Python :: 3
Requires-Python: >=3
